setup.py
target/__init__.py
target/cmd.py
target/tail.py
target.egg-info/PKG-INFO
target.egg-info/SOURCES.txt
target.egg-info/dependency_links.txt
target.egg-info/entry_points.txt
target.egg-info/requires.txt
target.egg-info/top_level.txt