Metadata-Version: 1.1
Name: target
Version: 0.0.10
Summary: a performance measurement stub
Home-page: UNKNOWN
Author: Alexey Lavrenuke (load testing)
Author-email: direvius@yandex-team.ru
License: MPLv2
Platform: UNKNOWN
Classifier: Environment :: Web Environment
Classifier: Intended Audience :: Developers
Classifier: Intended Audience :: System Administrators
Classifier: Operating System :: POSIX
Classifier: Topic :: Software Development :: Quality Assurance
Classifier: Topic :: Software Development :: Testing
Classifier: Programming Language :: Python :: 2
Classifier: Programming Language :: Python :: 3
